{
  "अध्याय_मेटाडेटा": {
    "अध्याय_आईडी": "6.हिंदी.07",
    "कक्षा": "6",
    "विषय": "हिंदी",
    "अध्याय_का_नाम": "करना है निर्माण",
    "लेखक": "गौकरन वर्मा"
  },
  "बहुविकल्पीय_प्रश्न": [
    {
      "प्रश्न_आईडी": 1,
      "प्रश्न": "कविता 'करना है निर्माण' के कवि कौन हैं?",
      "विकल्प": [
        { "पाठ": "महात्मा गांधी", "सही_है": false },
        { "पाठ": "गौकरन वर्मा", "सही_है": true },
        { "पाठ": "साने गुरुजी", "सही_है": false },
        { "पाठ": "सुमित्रा नंदन पंत", "सही_है": false }
      ],
      "उत्तर": "गौकरन वर्मा"
    },
    {
      "प्रश्न_आईडी": 2,
      "प्रश्न": "कवि किसका निर्माण करने की बात कर रहे हैं?",
      "विकल्प": [
        { "पाठ": "मकान का", "सही_है": false },
        { "पाठ": "नव भारत का", "सही_है": true },
        { "पाठ": "कारखाने का", "सही_है": false },
        { "पाठ": "सड़क का", "सही_है": false }
      ],
      "उत्तर": "नव भारत का"
    },
    {
      "प्रश्न_आईडी": 3,
      "प्रश्न": "कवि के अनुसार हमें जग में किसकी शान बढ़ानी है?",
      "विकल्प": [
        { "पाठ": "स्वयं की", "सही_है": false },
        { "पाठ": "अपने देश की", "सही_है": true },
        { "पाठ": "अपने परिवार की", "सही_है": false },
        { "पाठ": "विदेशों की", "सही_है": false }
      ],
      "उत्तर": "अपने देश की"
    },
    {
      "प्रश्न_आईडी": 4,
      "प्रश्न": "खेतों में क्या लहराने की बात कही गई है?",
      "विकल्प": [
        { "पाठ": "पानी", "सही_है": false },
        { "पाठ": "हरियाली", "सही_है": true },
        { "पाठ": "मिट्टी", "सही_है": false },
        { "पाठ": "धुआं", "सही_है": false }
      ],
      "उत्तर": "हरियाली"
    },
    {
      "प्रश्न_आईडी": 5,
      "प्रश्न": "डालियाँ किन चीजों से झूम रही हों?",
      "विकल्प": [
        { "पाठ": "पत्तों से", "सही_है": false },
        { "पाठ": "फूल-फलों से", "सही_है": true },
        { "पाठ": "पक्षियों से", "सही_है": false },
        { "पाठ": "बर्फ से", "सही_है": false }
      ],
      "उत्तर": "फूल-फलों से"
    },
    {
      "प्रश्न_आईडी": 6,
      "प्रश्न": "नदी, नहर और बरखा के जल से क्या बरसेगा?",
      "विकल्प": [
        { "पाठ": "सोना", "सही_है": false },
        { "पाठ": "धान", "सही_है": true },
        { "पाठ": "चांदी", "सही_है": false },
        { "पाठ": "सिक्के", "सही_है": false }
      ],
      "उत्तर": "धान"
    },
    {
      "प्रश्न_आईडी": 7,
      "प्रश्न": "'सरवर' शब्द का सही अर्थ क्या है?",
      "विकल्प": [
        { "पाठ": "सागर", "सही_है": false },
        { "पाठ": "तालाब", "सही_है": true },
        { "पाठ": "नदी", "सही_है": false },
        { "पाठ": "आकाश", "सही_है": false }
      ],
      "उत्तर": "तालाब"
    },
    {
      "प्रश्न_आईडी": 8,
      "प्रश्न": "कवि ऊँचे शिखरों पर कहाँ फूल चढ़ाने की बात कर रहे हैं?",
      "विकल्प": [
        { "पाठ": "नीलगिरी पे", "सही_है": false },
        { "पाठ": "हिमगिरि पे", "सही_है": true },
        { "पाठ": "विंध्याचल पे", "सही_है": false },
        { "पाठ": "अरावली पे", "सही_है": false }
      ],
      "उत्तर": "हिमगिरि पे"
    },
    {
      "प्रश्न_आईडी": 9,
      "प्रश्न": "'रत्नाकर' शब्द किसके लिए प्रयुक्त हुआ है?",
      "विकल्प": [
        { "पाठ": "पर्वत", "सही_है": false },
        { "पाठ": "समुद्र", "सही_है": true },
        { "पाठ": "आकाश", "सही_है": false },
        { "पाठ": "पाताल", "सही_है": false }
      ],
      "उत्तर": "समुद्र"
    },
    {
      "प्रश्न_आईडी": 10,
      "प्रश्न": "समुद्र के तल से हमें क्या खोजकर लाना है?",
      "विकल्प": [
        { "पाठ": "मछलियाँ", "सही_है": false },
        { "पाठ": "रत्न", "सही_है": true },
        { "पाठ": "शंख", "सही_है": false },
        { "पाठ": "नमक", "सही_है": false }
      ],
      "उत्तर": "रत्न"
    },
    {
      "प्रश्न_आईडी": 11,
      "प्रश्न": "कवि किनके गान गाने की बात कर रहे हैं?",
      "विकल्प": [
        { "पाठ": "युद्ध के", "सही_है": false },
        { "पाठ": "कुंजों की मनहर सुंदरता के", "सही_है": true },
        { "पाठ": "अपनी प्रशंसा के", "सही_है": false },
        { "पाठ": "विदेशी कहानियों के", "सही_है": false }
      ],
      "उत्तर": "कुंजों की मनहर सुंदरता के"
    },
    {
      "प्रश्न_आईडी": 12,
      "प्रश्न": "हम सब आपस में क्या हैं?",
      "विकल्प": [
        { "पाठ": "दुश्मन", "सही_है": false },
        { "पाठ": "भाई-भाई", "सही_है": true },
        { "पाठ": "अजनबी", "सही_है": false },
        { "पाठ": "प्रतिद्वंद्वी", "सही_है": false }
      ],
      "उत्तर": "भाई-भाई"
    },
    {
      "प्रश्न_आईडी": 13,
      "प्रश्न": "भारत की संतानों में क्या होना चाहिए?",
      "विकल्प": [
        { "पाठ": "नफरत", "सही_है": false },
        { "पाठ": "सच्ची प्रेम भलाई", "सही_है": true },
        { "पाठ": "लालच", "सही_है": false },
        { "पाठ": "अहंकार", "सही_है": false }
      ],
      "उत्तर": "सच्ची प्रेम भलाई"
    },
    {
      "प्रश्न_आईडी": 14,
      "प्रश्न": "पत्थर में प्राण किससे प्रकटाने की बात की गई है?",
      "विकल्प": [
        { "पाठ": "जादू से", "सही_है": false },
        { "पाठ": "सत्य-अहिंसा के प्रण से", "सही_है": true },
        { "पाठ": "मशीनों से", "सही_है": false },
        { "पाठ": "हथियारों से", "सही_है": false }
      ],
      "उत्तर": "सत्य-अहिंसा के प्रण से"
    },
    {
      "प्रश्न_आईडी": 15,
      "प्रश्न": "'हिमगिरि' का अर्थ क्या है?",
      "विकल्प": [
        { "पाठ": "बर्फीला पानी", "सही_है": false },
        { "पाठ": "हिमालय", "सही_है": true },
        { "पाठ": "ऊंचा घर", "सही_है": false },
        { "पाठ": "छोटा पर्वत", "सही_है": false }
      ],
      "उत्तर": "हिमालय"
    },
    {
      "प्रश्न_आईडी": 16,
      "प्रश्न": "'अतल' शब्द का क्या अर्थ है?",
      "विकल्प": [
        { "पाठ": "समतल", "सही_है": false },
        { "पाठ": "अथाह/बहुत गहरा", "सही_है": true },
        { "पाठ": "ऊंचा", "सही_है": false },
        { "पाठ": "ठोस", "सही_है": false }
      ],
      "उत्तर": "अथाह/बहुत गहरा"
    },
    {
      "प्रश्न_आईडी": 17,
      "प्रश्न": "'नीर' शब्द का पर्यायवाची क्या है?",
      "विकल्प": [
        { "पाठ": "दूध", "सही_है": false },
        { "पाठ": "पानी", "सही_है": true },
        { "पाठ": "शहद", "सही_है": false },
        { "पाठ": "अमृत", "सही_है": false }
      ],
      "उत्तर": "पानी"
    },
    {
      "प्रश्न_आईडी": 18,
      "प्रश्न": "'मनहर' का समानार्थी शब्द क्या है?",
      "विकल्प": [
        { "पाठ": "डरावना", "सही_है": false },
        { "पाठ": "मनोहर (सुंदर)", "सही_है": true },
        { "पाठ": "उदास", "सही_है": false },
        { "पाठ": "कठोर", "सही_है": false }
      ],
      "उत्तर": "मनोहर (सुंदर)"
    },
    {
      "प्रश्न_आईडी": 19,
      "प्रश्न": "कवि के अनुसार हमें आपस में क्या मिटाना चाहिए?",
      "विकल्प": [
        { "पाठ": "प्रेम", "सही_है": false },
        { "पाठ": "भेदभाव", "सही_है": true },
        { "पाठ": "भाईचारा", "सही_है": false },
        { "पाठ": "एकता", "सही_है": false }
      ],
      "उत्तर": "भेदभाव"
    },
    {
      "प्रश्न_आईडी": 20,
      "प्रश्न": "कविता में किस देश की महिमा गाई गई है?",
      "विकल्प": [
        { "पाठ": "अमेरिका", "सही_है": false },
        { "पाठ": "भारत", "सही_है": true },
        { "पाठ": "जापान", "सही_है": false },
        { "पाठ": "रूस", "सही_है": false }
      ],
      "उत्तर": "भारत"
    },
    {
      "प्रश्न_आईडी": 21,
      "प्रश्न": "'करना है' क्रिया का कौन सा काल है?",
      "विकल्प": [
        { "पाठ": "भूतकाल", "सही_है": false },
        { "पाठ": "वर्तमान काल", "सही_है": true },
        { "पाठ": "भविष्य काल", "सही_है": false },
        { "पाठ": "पूर्ण भूतकाल", "सही_है": false }
      ],
      "उत्तर": "वर्तमान काल"
    },
    {
      "प्रश्न_आईडी": 22,
      "प्रश्न": "गौकरन वर्मा किस रूप में प्रसिद्ध हैं?",
      "विकल्प": [
        { "पाठ": "कहानीकार", "सही_है": false },
        { "पाठ": "क्रांति गीत निर्माता", "सही_है": true },
        { "पाठ": "उपन्यासकार", "सही_है": false },
        { "पाठ": "चित्रकार", "सही_है": false }
      ],
      "उत्तर": "क्रांति गीत निर्माता"
    },
    {
      "प्रश्न_आईडी": 23,
      "प्रश्न": "'बढ़ानी होगी' क्रिया किस काल को दर्शाती है?",
      "विकल्प": [
        { "पाठ": "वर्तमान", "सही_है": false },
        { "पाठ": "भविष्य", "सही_है": true },
        { "पाठ": "भूत", "सही_है": false },
        { "पाठ": "अपूर्ण वर्तमान", "सही_है": false }
      ],
      "उत्तर": "भविष्य"
    },
    {
      "प्रश्न_आईडी": 24,
      "प्रश्न": "कुंजों की सुंदरता कैसी है?",
      "विकल्प": [
        { "पाठ": "भयानक", "सही_है": false },
        { "पाठ": "मनहर", "सही_है": true },
        { "पाठ": "अंधेरी", "सही_है": false },
        { "पाठ": "बदसूरत", "सही_है": false }
      ],
      "उत्तर": "मनहर"
    },
    {
      "प्रश्न_आईडी": 25,
      "प्रश्न": "सत्य और अहिंसा क्या हैं?",
      "विकल्प": [
        { "पाठ": "हथियार", "सही_है": false },
        { "पाठ": "प्रण (संकल्प)", "सही_है": true },
        { "पाठ": "खेल", "सही_है": false },
        { "पाठ": "भोजन", "सही_है": false }
      ],
      "उत्तर": "प्रण (संकल्प)"
    },
    {
      "प्रश्न_आईडी": 26,
      "प्रश्न": "'शिखर' का अर्थ क्या है?",
      "विकल्प": [
        { "पाठ": "तल", "सही_है": false },
        { "पाठ": "चोटी", "सही_है": true },
        { "पाठ": "जड़", "सही_है": false },
        { "पाठ": "मैदान", "सही_है": false }
      ],
      "उत्तर": "चोटी"
    },
    {
      "प्रश्न_आईडी": 27,
      "प्रश्न": "कवि ने 'संतान' शब्द किसके लिए उपयोग किया है?",
      "विकल्प": [
        { "पाठ": "केवल बच्चों के लिए", "सही_है": false },
        { "पाठ": "भारत के सभी नागरिकों के लिए", "सही_है": true },
        { "पाठ": "जानवरों के लिए", "सही_है": false },
        { "पाठ": "पेड़ों के लिए", "सही_है": false }
      ],
      "उत्तर": "भारत के सभी नागरिकों के लिए"
    },
    {
      "प्रश्न_आईडी": 28,
      "प्रश्न": "'रत्नों पाएँ' में रत्न कहाँ से मिलेंगे?",
      "विकल्प": [
        { "पाठ": "पहाड़ से", "सही_है": false },
        { "पाठ": "रत्नाकर (समुद्र) से", "सही_है": true },
        { "पाठ": "आसमान से", "सही_है": false },
        { "पाठ": "बाजार से", "सही_है": false }
      ],
      "उत्तर": "रत्नाकर (समुद्र) से"
    },
    {
      "प्रश्न_आईडी": 29,
      "प्रश्न": "कविता में 'अतुल नीर' का क्या अर्थ है?",
      "विकल्प": [
        { "पाठ": "कम पानी", "सही_है": false },
        { "पाठ": "अपार/अथाह पानी", "सही_है": true },
        { "पाठ": "गंदा पानी", "सही_है": false },
        { "पाठ": "मीठा पानी", "सही_है": false }
      ],
      "उत्तर": "अपार/अथाह पानी"
    },
    {
      "प्रश्न_आईडी": 30,
      "प्रश्न": "स्वतंत्रता मेरा जन्मसिद्ध अधिकार है - यह किसका विचार है?",
      "विकल्प": [
        { "पाठ": "गांधी जी", "सही_है": false },
        { "पाठ": "लोकमान्य तिलक", "सही_है": true },
        { "पाठ": "नेहरू जी", "सही_है": false },
        { "पाठ": "भगत सिंह", "सही_है": false }
      ],
      "उत्तर": "लोकमान्य तिलक"
    },
    {
      "प्रश्न_आईडी": 31,
      "प्रश्न": "ऐतिहासिक इमारतों का संरक्षण करना हमारा क्या है?",
      "विकल्प": [
        { "पाठ": "बोझ", "सही_है": false },
        { "पाठ": "कर्तव्य", "सही_है": true },
        { "पाठ": "शौक", "सही_है": false },
        { "पाठ": "व्यापार", "सही_है": false }
      ],
      "उत्तर": "कर्तव्य"
    },
    {
      "प्रश्न_आईडी": 32,
      "प्रश्न": "कवि ने भारत को क्या बनाने का संकल्प लिया है?",
      "विकल्प": [
        { "पाठ": "पुराना भारत", "सही_है": false },
        { "पाठ": "नव भारत", "सही_है": true },
        { "पाठ": "गरीब भारत", "सही_है": false },
        { "पाठ": "छोटा भारत", "सही_है": false }
      ],
      "उत्तर": "नव भारत"
    },
    {
      "प्रश्न_आईडी": 33,
      "प्रश्न": "'डाली-डाली' में कौन सा अलंकार या शब्द प्रयोग है?",
      "विकल्प": [
        { "पाठ": "विलोम", "सही_है": false },
        { "पाठ": "पुनरुक्ति", "सही_है": true },
        { "पाठ": "पर्यायवाची", "सही_है": false },
        { "पाठ": "विदेशी", "सही_है": false }
      ],
      "उत्तर": "पुनरुक्ति"
    },
    {
      "प्रश्न_आईडी": 34,
      "प्रश्न": "कवि के अनुसार शांति कैसे स्थापित हो सकती है?",
      "विकल्प": [
        { "पाठ": "युद्ध से", "सही_है": false },
        { "पाठ": "आपसी प्रेम और सत्य-अहिंसा से", "सही_है": true },
        { "पाठ": "चुप रहकर", "सही_है": false },
        { "पाठ": "डर से", "सही_है": false }
      ],
      "उत्तर": "आपसी प्रेम और सत्य-अहिंसा से"
    },
    {
      "प्रश्न_आईडी": 35,
      "प्रश्न": "कविता में 'शान' शब्द का क्या अर्थ है?",
      "विकल्प": [
        { "पाठ": "घमंड", "सही_है": false },
        { "पाठ": "प्रतिष्ठा/गौरव", "सही_है": true },
        { "पाठ": "आराम", "सही_है": false },
        { "पाठ": "दिखावा", "सही_है": false }
      ],
      "उत्तर": "प्रतिष्ठा/गौरव"
    }
  ],
  "लघु_उत्तर_प्रश्न": [
    { "प्रश्न_आईडी": 1, "प्रश्न": "कविता का मुख्य उद्देश्य क्या है?", "उत्तर": "कविता का मुख्य उद्देश्य नव भारत का निर्माण करना और देश की शान बढ़ाना है।" },
    { "प्रश्न_आईडी": 2, "प्रश्न": "कवि नव भारत का निर्माण कैसे करना चाहता है?", "उत्तर": "कवि परिश्रम, एकता और गौरव बढ़ाकर नव भारत का निर्माण करना चाहता है।" },
    { "प्रश्न_आईडी": 3, "प्रश्न": "खेतों की हरियाली से क्या तात्पर्य है?", "उत्तर": "खेतों की हरियाली से तात्पर्य देश की संपन्नता और खुशहाली से है।" },
    { "प्रश्न_आईडी": 4, "प्रश्न": "कवि ने 'शान' शब्द का प्रयोग किसके लिए किया है?", "उत्तर": "कवि ने 'शान' शब्द का प्रयोग भारत देश के गौरव और मान-सम्मान के लिए किया है।" },
    { "प्रश्न_आईडी": 5, "प्रश्न": "डालियाँ क्यों झूम रही हैं?", "उत्तर": "डालियाँ फूल और फलों के बोझ और सुंदरता के कारण झूम रही हैं।" },
    { "प्रश्न_आई": 6, "प्रश्न": "नदी-नहरों के जल का क्या महत्व है?", "उत्तर": "नदी-नहरों के जल से खेतों की सिंचाई होती है जिससे भरपूर धान पैदा होता है।" },
    { "प्रश्न_आईडी": 7, "प्रश्न": "हिमगिरि के शिखरों पर फूल चढ़ाने का क्या अर्थ है?", "उत्तर": "इसका अर्थ है हिमालय जैसी ऊँचाइयों को छूना और देश के गौरव के लिए सर्वस्व अर्पण करना।" },
    { "प्रश्न_आईडी": 8, "प्रश्न": "रत्नाकर से रत्न खोजने का क्या तात्पर्य है?", "उत्तर": "इसका तात्पर्य है समुद्र की गहराइयों से संसाधनों और ज्ञान रूपी रत्नों को प्राप्त करना।" },
    { "प्रश्न_आईडी": 9, "प्रश्न": "कुंजों की सुंदरता कैसी बताई गई है?", "उत्तर": "कुंजों की सुंदरता 'मनहर' यानी मन को हर लेने वाली और बहुत सुंदर बताई गई है।" },
    { "प्रश्न_आईडी": 10, "प्रश्न": "कवि ने 'भाई-भाई' किसे कहा है?", "उत्तर": "कवि ने भारत के सभी नागरिकों को आपस में भाई-भाई कहा है।" },
    { "प्रश्न_आईडी": 11, "प्रश्न": "आपसी भेदभाव मिटाने से क्या होगा?", "उत्तर": "आपसी भेदभाव मिटाने से एकता बढ़ेगी और देश का निर्माण तेजी से होगा।" },
    { "प्रश्न_आईडी": 12, "प्रश्न": "सत्य और अहिंसा के प्रण का क्या महत्व है?", "उत्तर": "सत्य और अहिंसा के संकल्प से कठिन से कठिन कार्य (पत्थर में प्राण) संभव हो सकते हैं।" },
    { "प्रश्न_आईडी": 13, "प्रश्न": "कविता में किन प्राकृतिक संसाधनों का वर्णन है?", "उत्तर": "कविता में हिमगिरि (पर्वत), रत्नाकर (समुद्र), नदी, नहर, सरवर और खेतों का वर्णन है।" },
    { "प्रश्न_आईडी": 14, "प्रश्न": "कवि गौकरन वर्मा की प्रसिद्ध रचना कौन सी है?", "उत्तर": "कवि की प्रसिद्ध रचना 'उठो साथियो कदम मिलाकर' है।" },
    { "प्रश्न_आईडी": 15, "प्रश्न": "'निर्माण' शब्द का अर्थ स्पष्ट करें।", "उत्तर": "निर्माण का अर्थ है किसी नई चीज को बनाना या रचना करना।" },
    { "प्रश्न_आईडी": 16, "प्रश्न": "कवि जग में किसकी विजय गाथा गाना चाहता है?", "उत्तर": "कवि जग में भारत की सुंदरता और प्रगति की विजय गाथा गाना चाहता है।" },
    { "प्रश्न_आईडी": 17, "प्रश्न": "धान बरसने का क्या संकेत है?", "उत्तर": "इसका संकेत है कि अच्छी वर्षा और सिंचाई से प्रचुर मात्रा में अन्न उत्पादन होगा।" },
    { "प्रश्न_आईडी": 18, "प्रश्न": "अतुल नीर कहाँ पाया जाता है?", "उत्तर": "अतुल नीर रत्नाकर यानी समुद्र की गहराइयों में पाया जाता है।" },
    { "प्रश्न_आईडी": 19, "प्रश्न": "कवि ने भारत की संतानों को क्या सलाह दी है?", "उत्तर": "कवि ने सभी को सच्ची प्रेम भलाई के साथ मिलकर रहने की सलाह दी है।" },
    { "प्रश्न_आईडी": 20, "प्रश्न": "कविता में 'प्रण' शब्द का क्या अर्थ है?", "उत्तर": "प्रण का अर्थ है पक्का इरादा या प्रतिज्ञा करना।" },
    { "प्रश्न_आईडी": 21, "प्रश्न": "पत्थर में प्राण प्रकटने का मुहावरेदार अर्थ क्या है?", "उत्तर": "इसका अर्थ है असंभव कार्य को संभव कर दिखाना।" },
    { "प्रश्न_आईडी": 22, "प्रश्न": "कवि किसके गान गाना चाहता है?", "उत्तर": "कवि वन और कुंजों की मनोहर सुंदरता के गान गाना चाहता है।" },
    { "प्रश्न_आईडी": 23, "प्रश्न": "भारत की विविधता क्या है?", "उत्तर": "भारत में अलग-अलग भाषा, धर्म और भौगोलिक विविधताएँ (पहाड़, समुद्र, नदियाँ) पाई जाती हैं।" },
    { "प्रश्न_आईडी": 24, "प्रश्न": "'सरवर' और 'रत्नाकर' में क्या अंतर है?", "उत्तर": "सरवर का अर्थ तालाब होता है और रत्नाकर का अर्थ समुद्र होता है।" },
    { "प्रश्न_आईडी": 25, "प्रश्न": "कवि ने नई पीढ़ी को क्या संदेश दिया है?", "उत्तर": "कवि ने नई पीढ़ी को देश के प्रति कर्तव्य निभाने और नव निर्माण करने का संदेश दिया है।" },
    { "प्रश्न_आईडी": 26, "प्रश्न": "कविता की भाषा कैसी है?", "उत्तर": "कविता की भाषा सरल, ओजपूर्ण और प्रेरणादायक है।" },
    { "प्रश्न_आईडी": 27, "प्रश्न": "क्या हिमालय की बर्फ पिघलनी बंद हो जाए तो क्या होगा?", "उत्तर": "यदि बर्फ पिघलनी बंद हो गई तो उत्तर भारत की नदियाँ सूख जाएँगी और खेती व जीवन संकट में पड़ जाएगा।" },
    { "प्रश्न_आईडी": 28, "प्रश्न": "परमवीर चक्र प्राप्त सैनिकों की सूची क्यों बनानी चाहिए?", "उत्तर": "ताकि हम उनके बलिदान से प्रेरणा ले सकें और उनमें देशप्रेम की भावना जागृत हो।" },
    { "प्रश्न_आईडी": 29, "प्रश्न": "ऐतिहासिक इमारतों का संरक्षण क्यों जरूरी है?", "उत्तर": "क्योंकि ये हमारी सांस्कृतिक विरासत और गौरवशाली इतिहास की प्रतीक हैं।" },
    { "प्रश्न_आईडी": 30, "प्रश्न": "देशभक्ति पर आधारित कविता सुनने से क्या लाभ होता है?", "उत्तर": "इससे मन में देश के प्रति सम्मान और कुछ कर गुजरने का उत्साह बढ़ता है।" },
    { "प्रश्न_आईडी": 31, "प्रश्न": "वैज्ञानिक आविष्कारों का देश निर्माण में क्या योगदान है?", "उत्तर": "वैज्ञानिक आविष्कारों से देश आधुनिक बनता है और लोगों का जीवन स्तर सुधरता है।" },
    { "प्रश्न_आईडी": 32, "प्रश्न": "कवि ने एकता पर जोर क्यों दिया है?", "उत्तर": "क्योंकि बिना एकता के देश का विकास और सुरक्षा संभव नहीं है।" },
    { "प्रश्न_आईडी": 33, "प्रश्न": "'अतल' का विलोम क्या होगा?", "उत्तर": "अतल का विलोम 'समतल' या 'उथला' हो सकता है।" },
    { "प्रश्न_आईडी": 34, "प्रश्न": "कवि भारत को विश्व में कैसा स्थान दिलाना चाहता है?", "उत्तर": "कवि भारत को विश्व में सबसे ऊँचा और सम्मानित स्थान दिलाना चाहता है।" },
    { "प्रश्न_आईडी": 35, "प्रश्न": "'शान बढ़ाना' मुहावरे का वाक्य प्रयोग करें।", "उत्तर": "भारतीय खिलाड़ियों ने ओलंपिक में स्वर्ण पदक जीतकर देश की शान बढ़ाई।" },
    { "प्रश्न_आईडी": 36, "प्रश्न": "फूल-फलों से लदी डालियाँ किसका प्रतीक हैं?", "उत्तर": "ये समृद्धि और खुशहाली का प्रतीक हैं।" },
    { "प्रश्न_आईडी": 37, "प्रश्न": "सत्य-अहिंसा के मार्ग पर चलने से क्या लाभ है?", "उत्तर": "इस मार्ग पर चलने से बिना किसी हिंसा के समाज में शांति और बदलाव लाया जा सकता है।" },
    { "प्रश्न_आईडी": 38, "प्रश्न": "कविता में 'कल' शब्द का प्रयोग किसके लिए हुआ है?", "उत्तर": "कविता के अभ्यास में 'कल' का प्रयोग समय (बीता हुआ या आने वाला) के संदर्भ में हुआ है।" },
    { "प्रश्न_आईडी": 39, "प्रश्न": "कुंज का क्या अर्थ है?", "उत्तर": "कुंज का अर्थ पेड़ों और लताओं से घिरा हुआ सुंदर स्थान या बगीचा है।" },
    { "प्रश्न_आईडी": 40, "प्रश्न": "कवि के अनुसार 'सच्ची प्रेम भलाई' क्या है?", "उत्तर": "निस्वार्थ भाव से दूसरों की मदद करना और सभी से प्रेम करना ही सच्ची भलाई है।" },
    { "प्रश्न_आईडी": 41, "प्रश्न": "भारत की विशेषताएँ क्या हैं?", "उत्तर": "भारत अपनी गंगा-जमुनी तहजीब, हिमालय और समुद्र जैसी प्राकृतिक सुंदरता के लिए प्रसिद्ध है।" },
    { "प्रश्न_आईडी": 42, "प्रश्न": "कविता में 'धरती' को क्या माना गया है?", "उत्तर": "धरती को अपनी माँ और कर्मभूमि माना गया है जिसे हरा-भरा बनाना है।" },
    { "प्रश्न_आईडी": 43, "प्रश्न": "कवि ने 'कदम मिलाकर' चलने को क्यों कहा है?", "उत्तर": "ताकि सभी देशवासी एक साथ मिलकर लक्ष्य प्राप्त कर सकें।" },
    { "प्रश्न_आईडी": 44, "प्रश्न": "रत्नाकर का संधि विच्छेद क्या होगा?", "उत्तर": "रत्न + आकर (रत्नों का खान)।" },
    { "प्रश्न_आईडी": 45, "प्रश्न": "मनहर सुंदरता कहाँ बिखरी है?", "उत्तर": "मनहर सुंदरता भारत के वनों, कुंजों और घाटियों में बिखरी है।" },
    { "प्रश्न_आईडी": 46, "प्रश्न": "कविता में आए किन्हीं दो तत्सम शब्दों को लिखें।", "उत्तर": "शिखर, रत्नाकर।" },
    { "प्रश्न_आईडी": 47, "प्रश्न": "कवि ने 'धान' शब्द का प्रयोग क्यों किया है?", "उत्तर": "धान भारत की प्रमुख फसल है और यह कृषि प्रधान देश की संपन्नता को दर्शाता है।" },
    { "प्रश्न_आईडी": 48, "प्रश्न": "अतुल नीर को खोजने का क्या अर्थ है?", "उत्तर": "इसका अर्थ है संसाधनों का सही उपयोग करना और नई खोजें करना।" },
    { "प्रश्न_आईडी": 49, "प्रश्न": "कवि ने आपस के भेदों को मिटाने के लिए क्या कहा है?", "उत्तर": "कवि ने कहा कि हम सब एक ही भारत माँ की संतान हैं, इसलिए कोई भेद नहीं रहना चाहिए।" },
    { "प्रश्न_आईडी": 50, "प्रश्न": "'पत्थर' शब्द यहाँ किसके लिए आया है?", "उत्तर": "पत्थर यहाँ जड़ता, आलस और कठिन बाधाओं के लिए आया है।" },
    { "प्रश्न_आईडी": 51, "प्रश्न": "हिंसा का विलोम शब्द क्या है?", "उत्तर": "अहिंसा।" },
    { "प्रश्न_आईडी": 52, "प्रश्न": "कवि की दृष्टि में 'नव भारत' कैसा होगा?", "उत्तर": "कवि की दृष्टि में नव भारत शिक्षित, संपन्न, एकताबद्ध और गौरवशाली होगा।" },
    { "प्रश्न_आईडी": 53, "प्रश्न": "कविता में आए काल के उदाहरण दें।", "उत्तर": "करना है (वर्तमान), बढ़ानी होगी (भविष्य)।" },
    { "प्रश्न_आईडी": 54, "प्रश्न": "कवि ने शिखरों पर फूल चढ़ाने की बात क्यों कही?", "उत्तर": "क्योंकि ऊँचे शिखर महान लक्ष्यों के प्रतीक हैं।" },
    { "प्रश्न_आईडी": 55, "प्रश्न": "'सच्ची प्रेम भलाई' का समाज पर क्या असर पड़ता है?", "उत्तर": "इससे समाज में शांति, विश्वास और भाईचारा बढ़ता है।" },
    { "प्रश्न_आईडी": 56, "प्रश्न": "कुंजों की सुंदरता का गान कौन गाएगा?", "उत्तर": "देशवासी और कवि स्वयं कुंजों की सुंदरता का गान गाएंगे।" },
    { "प्रश्न_आईडी": 57, "प्रश्न": "क्या यह कविता देशभक्ति की श्रेणी में आती है?", "उत्तर": "हाँ, यह एक शुद्ध देशभक्ति और प्रेरणादायक कविता है।" },
    { "प्रश्न_आईडी": 58, "प्रश्न": "कवि ने 'जग' शब्द का प्रयोग क्यों किया?", "उत्तर": "कवि भारत की ख्याति पूरी दुनिया (जग) में फैलाना चाहता है।" },
    { "प्रश्न_आईडी": 59, "प्रश्न": "प्रस्तुत कविता से हमें क्या प्रेरणा मिलती है?", "उत्तर": "हमें अपने देश की प्रगति के लिए निरंतर प्रयास करने और मिलजुलकर रहने की प्रेरणा मिलती है।" },
    { "प्रश्न_आईडी": 60, "प्रश्न": "अन्तिम पंक्तियों में कवि ने किस पर बल दिया है?", "उत्तर": "कवि ने सत्य, अहिंसा और एकता पर सबसे अधिक बल दिया है।" }
  ]
}